{"credit":"Davis Instruments Corp.","credit_URL":"http:\/\/www.davisnet.com","disclaimer_url":"http:\/\/www.davisnet.com\/about\/terms.asp","copyright_url":"http:\/\/www.davisnet.com\/about\/terms.asp","privacy_policy_url":"http:\/\/www.davisnet.com\/about\/privacy.asp","image":{"url":"http:\/\/www.weatherlink.com\/images\/Logo_Davis_reflxblu.jpg","title":"Davis WeatherLink","link":"http:\/\/www.weatherlink.com"},"suggested_pickup":"15 minutes after the hour","suggested_pickup_period":"60","dewpoint_c":"4.4","dewpoint_f":"40.0","dewpoint_string":"40.0 F (4.4 C)","heat_index_c":"10.6","heat_index_f":"51.0","heat_index_string":"51.0 F (10.6 C)","location":"USA","latitude":"45.8","longitude":"6.9","observation_time":"Last Updated on Mar 8 2019, 7:15 pm CET","observation_time_rfc822":"Fri, 8 Mar 2019 19:15:12 +0100","pressure_in":"30.103","pressure_mb":"1019.4","pressure_string":"1019.4 mb","relative_humidity":"64","station_id":"demo","temp_c":"11.0","temp_f":"51.8","temperature_string":"51.8 F (11.0 C)","wind_degrees":"344","wind_dir":"North-northwest","wind_kt":"3.5","wind_mph":"4.0","windchill_c":"11.1","windchill_f":"52.0","windchill_string":"52.0 F (11.1 C)","davis_current_observation":{"DID":"001D0A00DE6A","station_name":"API","observation_age":13266181,"dewpoint_day_high_f":"42","dewpoint_day_high_time":"12:56am","dewpoint_day_low_f":"37","dewpoint_day_low_time":"7:11am","dewpoint_month_high_f":"57","dewpoint_month_low_f":"37","dewpoint_year_high_f":"58","dewpoint_year_low_f":"14","et_day":"0.037","et_month":"0.360","et_year":"4.250","heat_index_day_high_f":"51","heat_index_day_high_time":"9:12am","heat_index_month_high_f":"60","heat_index_year_high_f":"66","leaf_wetness_1_month_high":"15","leaf_wetness_1_month_low":"15","leaf_wetness_1_year_high":"15","leaf_wetness_1_year_low":"15","leaf_wetness_2":"1","leaf_wetness_2_day_high":"8","leaf_wetness_2_day_high_time":"1:02am","leaf_wetness_2_day_low":"1","leaf_wetness_2_day_low_time":"8:01am","leaf_wetness_2_month_high":"15","leaf_wetness_2_month_low":"1","leaf_wetness_2_year_high":"15","leaf_wetness_2_year_low":"0","pressure_day_high_in":"30.105","pressure_day_high_time":"9:33am","pressure_day_low_in":"30.001","pressure_day_low_time":"3:19am","pressure_month_high_in":"30.170","pressure_month_low_in":"29.598","pressure_tendency_string":"Rising Slowly","pressure_year_high_in":"30.468","pressure_year_low_in":"29.381","rain_day_in":"0.0079","rain_month_in":"1.2205","rain_rate_day_high_in_per_hr":"0.0079","rain_rate_day_high_time":"2:00am","rain_rate_hour_high_in_per_hr":"0.0000","rain_rate_in_per_hr":"0.0000","rain_rate_month_high_in_per_hr":"1.0157","rain_rate_year_high_in_per_hr":"28.3465","rain_storm_in":"0.6378","rain_storm_start_date":"3\/4\/2019","rain_year_in":"6.5512","relative_humidity_day_high":"78","relative_humidity_day_high_time":"12:59am","relative_humidity_day_low":"62","relative_humidity_day_low_time":"10:10am","relative_humidity_month_high":"95","relative_humidity_month_low":"62","relative_humidity_year_high":"96","relative_humidity_year_low":"20","relative_humidity_in":"21","relative_humidity_in_day_high":"27","relative_humidity_in_day_high_time":"12:29am","relative_humidity_in_day_low":"20","relative_humidity_in_day_low_time":"8:15am","relative_humidity_in_month_high":"40","relative_humidity_in_month_low":"20","relative_humidity_in_year_high":"43","relative_humidity_in_year_low":"5","relative_humidity_1":"65","relative_humidity_1_day_high":"79","relative_humidity_1_day_high_time":"1:00am","relative_humidity_1_day_low":"63","relative_humidity_1_day_low_time":"9:50am","relative_humidity_1_month_high":"97","relative_humidity_1_month_low":"62","relative_humidity_1_year_high":"98","relative_humidity_1_year_low":"21","soil_moisture_1":"23","soil_moisture_1_day_high":"24","soil_moisture_1_day_high_time":"5:32am","soil_moisture_1_day_low":"23","soil_moisture_1_day_low_time":"12:00am","soil_moisture_1_month_high":"24","soil_moisture_1_month_low":"9","soil_moisture_1_year_high":"122","soil_moisture_1_year_low":"4","soil_moisture_2":"90","soil_moisture_2_day_high":"90","soil_moisture_2_day_high_time":"10:07am","soil_moisture_2_day_low":"83","soil_moisture_2_day_low_time":"12:00am","soil_moisture_2_month_high":"90","soil_moisture_2_month_low":"43","soil_moisture_2_year_high":"200","soil_moisture_2_year_low":"10","solar_radiation":"712","solar_radiation_day_high":"712","solar_radiation_day_high_time":"10:13am","solar_radiation_month_high":"877","solar_radiation_year_high":"889","sunrise":"6:59am","sunset":"6:28pm","temp_day_high_f":"51.8","temp_day_high_time":"10:08am","temp_day_low_f":"47.6","temp_day_low_time":"6:06am","temp_month_high_f":"60.0","temp_month_low_f":"44.8","temp_year_high_f":"67.1","temp_year_low_f":"35.5","temp_extra_1":"51.0","temp_extra_1_day_high":"52.0","temp_extra_1_day_high_time":"10:08am","temp_extra_1_day_low":"47.0","temp_extra_1_day_low_time":"6:00am","temp_extra_1_month_high":"60.0","temp_extra_1_month_low":"44.0","temp_extra_1_year_high":"67.0","temp_extra_1_year_low":"35.0","temp_extra_2_year_high":"68.0","temp_extra_2_year_low":"68.0","temp_in_day_high_f":"73.1","temp_in_day_high_time":"9:35am","temp_in_day_low_f":"70.5","temp_in_day_low_time":"6:33am","temp_in_f":"73.0","temp_in_month_high_f":"76.1","temp_in_month_low_f":"70.5","temp_in_year_high_f":"77.1","temp_in_year_low_f":"67.1","temp_leaf_1":"52.0","temp_leaf_1_day_high":"54.0","temp_leaf_1_day_high_time":"12:00am","temp_leaf_1_day_low":"52.0","temp_leaf_1_day_low_time":"8:40am","temp_leaf_1_month_high":"55.0","temp_leaf_1_month_low":"52.0","temp_leaf_1_year_high":"57.0","temp_leaf_1_year_low":"49.0","temp_leaf_2":"52.0","temp_leaf_2_day_high":"52.0","temp_leaf_2_day_high_time":"10:07am","temp_leaf_2_day_low":"46.0","temp_leaf_2_day_low_time":"5:30am","temp_leaf_2_month_high":"71.0","temp_leaf_2_month_low":"44.0","temp_leaf_2_year_high":"86.0","temp_leaf_2_year_low":"34.0","temp_soil_1":"52.0","temp_soil_1_day_high":"54.0","temp_soil_1_day_high_time":"12:00am","temp_soil_1_day_low":"52.0","temp_soil_1_day_low_time":"8:40am","temp_soil_1_month_high":"55.0","temp_soil_1_month_low":"52.0","temp_soil_1_year_high":"57.0","temp_soil_1_year_low":"49.0","temp_soil_2":"52.0","temp_soil_2_day_high":"52.0","temp_soil_2_day_high_time":"10:07am","temp_soil_2_day_low":"46.0","temp_soil_2_day_low_time":"5:30am","temp_soil_2_month_high":"71.0","temp_soil_2_month_low":"44.0","temp_soil_2_year_high":"86.0","temp_soil_2_year_low":"34.0","temp_soil_3":"52.0","temp_soil_3_day_high":"52.0","temp_soil_3_day_high_time":"10:07am","temp_soil_3_day_low":"46.0","temp_soil_3_day_low_time":"5:52am","temp_soil_3_month_high":"70.0","temp_soil_3_month_low":"44.0","temp_soil_3_year_high":"85.0","temp_soil_3_year_low":"35.0","temp_soil_4":"51.0","temp_soil_4_day_high":"51.0","temp_soil_4_day_high_time":"9:23am","temp_soil_4_day_low":"46.0","temp_soil_4_day_low_time":"5:25am","temp_soil_4_month_high":"69.0","temp_soil_4_month_low":"44.0","temp_soil_4_year_high":"84.0","temp_soil_4_year_low":"34.0","uv_index":"3.1","uv_index_day_high":"3.1","uv_index_day_high_time":"10:13am","uv_index_month_high":"5.2","uv_index_year_high":"5.8","wind_day_high_mph":"23.0","wind_day_high_time":"12:46am","wind_month_high_mph":"27.0","wind_ten_min_avg_mph":"8.0","wind_ten_min_gust_mph":"17.0","wind_year_high_mph":"36.0","windchill_day_low_f":"42","windchill_day_low_time":"12:54am","windchill_month_low_f":"42","windchill_year_low_f":"34"},"time_to_generate":"0.010098 seconds"}
